setup.py
urlymath/__init__.py
urlymath.egg-info/PKG-INFO
urlymath.egg-info/SOURCES.txt
urlymath.egg-info/dependency_links.txt
urlymath.egg-info/top_level.txt
urlymath/common/__init__.py
urlymath/common/exceptions.py
urlymath/parse/__init__.py
urlymath/parse/parse.py
urlymath/tests/unittests.py