Metadata-Version: 1.0
Name: urlymath
Version: 0.9
Summary: Tools for playing with URLs.
Home-page: https://github.com/danluba/urlymath
Author: Dan Luba
Author-email: d@nluba.com
License: MIT
Platform: UNKNOWN
